flame/__init__.py
flame/__main__.py
flame/config.py
flame/exception.py
flame/flame_shell.py
flame/format.py
flame/license_db.py
flame/var/ambiguities.json
flame/var/compounds.json
flame/var/duals.json
flame/var/license_schema.json
flame/var/no_version.json
flame/var/operators.json
flame/var/licenses/0BSD.LICENSE
flame/var/licenses/0BSD.json
flame/var/licenses/AAL.LICENSE
flame/var/licenses/AAL.json
flame/var/licenses/AFL-1.1.LICENSE
flame/var/licenses/AFL-1.1.json
flame/var/licenses/AFL-1.2.LICENSE
flame/var/licenses/AFL-1.2.json
flame/var/licenses/AFL-2.0.LICENSE
flame/var/licenses/AFL-2.0.json
flame/var/licenses/AFL-2.1.LICENSE
flame/var/licenses/AFL-2.1.json
flame/var/licenses/AFL-3.0.LICENSE
flame/var/licenses/AFL-3.0.json
flame/var/licenses/AGPL-1.0-only.LICENSE
flame/var/licenses/AGPL-1.0-only.json
flame/var/licenses/AGPL-1.0-or-later.LICENSE
flame/var/licenses/AGPL-1.0-or-later.json
flame/var/licenses/AGPL-3.0-only.LICENSE
flame/var/licenses/AGPL-3.0-only.json
flame/var/licenses/AGPL-3.0-or-later.LICENSE
flame/var/licenses/AGPL-3.0-or-later.json
flame/var/licenses/APSL-2.0.LICENSE
flame/var/licenses/APSL-2.0.json
flame/var/licenses/Apache-1.0.LICENSE
flame/var/licenses/Apache-1.0.json
flame/var/licenses/Apache-1.1.LICENSE
flame/var/licenses/Apache-1.1.json
flame/var/licenses/Apache-2.0.LICENSE
flame/var/licenses/Apache-2.0.json
flame/var/licenses/Artistic-1.0-Perl.LICENSE
flame/var/licenses/Artistic-1.0-Perl.json
flame/var/licenses/Artistic-1.0.LICENSE
flame/var/licenses/Artistic-1.0.json
flame/var/licenses/Artistic-2.0.LICENSE
flame/var/licenses/Artistic-2.0.json
flame/var/licenses/Autoconf-exception-2.0.LICENSE
flame/var/licenses/Autoconf-exception-2.0.json
flame/var/licenses/Autoconf-exception-3.0.LICENSE
flame/var/licenses/Autoconf-exception-3.0.json
flame/var/licenses/BSD-1-Clause.LICENSE
flame/var/licenses/BSD-1-Clause.json
flame/var/licenses/BSD-2-Clause-Patent.LICENSE
flame/var/licenses/BSD-2-Clause-Patent.json
foss_flame-0.21.5.dist-info/CC-BY-4.0.txt
foss_flame-0.21.5.dist-info/GPL-3.0-or-later.txt
foss_flame-0.21.5.dist-info/METADATA
foss_flame-0.21.5.dist-info/WHEEL
foss_flame-0.21.5.dist-info/entry_points.txt
foss_flame-0.21.5.dist-info/top_level.txt
foss_flame-0.21.5.dist-info/RECORD
